{"stats":{"minecraft:custom":{"minecraft:time_since_rest":2655,"minecraft:leave_game":1,"minecraft:sprint_one_cm":33,"minecraft:play_time":2655,"minecraft:time_since_death":2655,"minecraft:walk_one_cm":23089,"minecraft:total_world_time":2666,"minecraft:fly_one_cm":44,"minecraft:jump":14},"minecraft:used":{"minecraft:redstone_torch":135,"minecraft:slime_block":28,"minecraft:netherite_pickaxe":447,"minecraft:piston":266},"minecraft:mined":{"minecraft:redstone_torch":131,"minecraft:slime_block":28,"minecraft:netherrack":18,"minecraft:piston":272},"minecraft:picked_up":{"minecraft:redstone_torch":130,"minecraft:netherrack":17,"minecraft:slime_block":27,"minecraft:piston":250}},"DataVersion":2975}